{"status":"success","data":[{"__name__":"http_request_duration_seconds_count","code":"200","instance":"restaurant:5006","job":"restaurant-service","method":"GET","route":"/metrics"},{"__name__":"http_request_duration_seconds_count","code":"200","instance":"order-service:5002","job":"order-service","method":"GET","route":"/metrics"},{"__name__":"http_request_duration_seconds_count","code":"200","instance":"auth-service:5001","job":"auth-service","method":"GET","route":"/metrics"},{"__name__":"http_request_duration_seconds_count","code":"200","instance":"delivery-service:5004","job":"delivery-service","method":"GET","route":"/metrics"},{"__name__":"http_request_duration_seconds_count","code":"200","instance":"admin-service:5008","job":"admin-service","method":"GET","route":"/metrics"},{"__name__":"http_request_duration_seconds_count","code":"200","instance":"payment-service:5004","job":"payment-service","method":"GET","route":"/metrics"},{"__name__":"http_request_duration_seconds_count","code":"301","instance":"order-service:5002","job":"order-service","method":"GET","route":"/"},{"__name__":"http_request_duration_seconds_count","code":"200","instance":"order-service:5002","job":"order-service","method":"GET","route":"/"},{"__name__":"http_request_duration_seconds_count","code":"200","instance":"order-service:5002","job":"order-service","method":"GET","route":"/swagger-ui.css"},{"__name__":"http_request_duration_seconds_count","code":"200","instance":"order-service:5002","job":"order-service","method":"GET","route":"/swagger-ui-init.js"},{"__name__":"http_request_duration_seconds_count","code":"200","instance":"order-service:5002","job":"order-service","method":"GET","route":"/swagger-ui-standalone-preset.js"},{"__name__":"http_request_duration_seconds_count","code":"200","instance":"order-service:5002","job":"order-service","method":"GET","route":"/swagger-ui-bundle.js"},{"__name__":"http_request_duration_seconds_count","code":"200","instance":"order-service:5002","job":"order-service","method":"GET","route":"/favicon-32x32.png"},{"__name__":"http_request_duration_seconds_count","code":"404","instance":"auth-service:5001","job":"auth-service","method":"GET","route":"/favicon.ico"},{"__name__":"http_request_duration_seconds_count","code":"201","instance":"auth-service:5001","job":"auth-service","method":"POST","route":"/register"},{"__name__":"http_request_duration_seconds_count","code":"200","instance":"auth-service:5001","job":"auth-service","method":"POST","route":"/login"},{"__name__":"http_request_duration_seconds_count","code":"200","instance":"auth-service:5001","job":"auth-service","method":"POST","route":"/logout"}]}
